Metadata-Version: 1.1
Name: pyinfo
Version: 1.0.1
Summary: python environment info as phpinfo does with php
Home-page: https://github.com/mastropinguino/pyinfo
Author: Vincenzo Farruggia
Author-email: mastropinguino@networky.net
License: UNKNOWN
Keywords: python info,pyinfo,environment information
Platform: UNKNOWN
Classifier: Development Status :: 5 - Production/Stable
Classifier: Environment :: Console
Classifier: Environment :: Web Environment
Classifier: Intended Audience :: Developers
Classifier: Intended Audience :: System Administrators
Classifier: License :: OSI Approved :: MIT License
Classifier: Operating System :: OS Independent
Classifier: Programming Language :: Python :: 2
Classifier: Programming Language :: Python :: 2.7
Classifier: Programming Language :: Python :: 3
Classifier: Programming Language :: Python :: 3.4
Classifier: Programming Language :: Python :: 3.5
Classifier: Topic :: Terminals
Classifier: Topic :: Utilities
